pyfunctions/__init__.py
pyfunctions/os.py
flinch-0.1.dist-info/LICENSE
flinch-0.1.dist-info/METADATA
flinch-0.1.dist-info/WHEEL
flinch-0.1.dist-info/top_level.txt
flinch-0.1.dist-info/RECORD
