Metadata-Version: 2.1
Name: flinch
Version: 0.1
Summary: python functions
Home-page: https://github.com/pankajr141/flinch
Author: Pankaj Rawat
Author-email: pankajr141@gmail.com
Classifier: Programming Language :: Python :: 3
Classifier: License :: OSI Approved :: MIT License
Classifier: Operating System :: OS Independent
License-File: LICENSE
Requires-Dist: numpy (>=1.23.0)
